metaverse/__init__.py
metaverse/bot.py
metaverse/const.py
metaverse/eventtarget.py
metaverse/httpclient.py
metaverse/llsd.py
metaverse/login.py
metaverse-0.0.3.dist-info/licenses/LICENSE.md
metaverse-0.0.3.dist-info/METADATA
metaverse-0.0.3.dist-info/WHEEL
metaverse-0.0.3.dist-info/top_level.txt
metaverse-0.0.3.dist-info/RECORD
