Metadata-Version: 2.4
Name: Metaverse
Version: 0.0.3
Summary: A library for handling Second Life things.
Home-page: https://github.com/FelixWolf/pymetaverse
Author: Félix
Author-email: felix.wolfz@gmail.com
Classifier: Development Status :: 3 - Alpha
Classifier: Intended Audience :: Developers
Classifier: Natural Language :: English
Classifier: Operating System :: OS Independent
Classifier: Programming Language :: Python
Classifier: Programming Language :: Python :: 3
Classifier: License :: OSI Approved :: zlib/libpng License
Classifier: Topic :: Software Development :: Libraries
License-File: LICENSE.md
Dynamic: author
Dynamic: author-email
Dynamic: classifier
Dynamic: description
Dynamic: description-content-type
Dynamic: home-page
Dynamic: license-file
Dynamic: summary
